[
{
  "lesson": 1,
  "words": [
    {"kana":"わたし","kanji":"私","meaning":"I"},
    {"kana":"わたしたち","kanji":"私たち","meaning":"we"},
    {"kana":"あなた","kanji":"あなた","meaning":"you"},
    {"kana":"あのひと","kanji":"あの人","meaning":"that person, he, she"},
    {"kana":"あのかた","kanji":"あの方","meaning":"that person (polite)"},
    {"kana":"みなさん","kanji":"皆さん","meaning":"ladies and gentlemen, everyone"},
    {"kana":"〜さん","kanji":"〜さん","meaning":"Mr./Ms. title"},
    {"kana":"〜ちゃん","kanji":"〜ちゃん","meaning":"child name suffix"},
    {"kana":"〜じん","kanji":"〜人","meaning":"nationality suffix"},
    {"kana":"せんせい","kanji":"先生","meaning":"teacher"},
    {"kana":"きょうし","kanji":"教師","meaning":"teacher, instructor"},
    {"kana":"がくせい","kanji":"学生","meaning":"student"},
    {"kana":"かいしゃいん","kanji":"会社員","meaning":"company employee"},
    {"kana":"しゃいん","kanji":"社員","meaning":"employee of company"},
    {"kana":"ぎんこういん","kanji":"銀行員","meaning":"bank employee"},
    {"kana":"いしゃ","kanji":"医者","meaning":"medical doctor"},
    {"kana":"けんきゅうしゃ","kanji":"研究者","meaning":"researcher"},
    {"kana":"エンジニア","kanji":"エンジニア","meaning":"engineer"},
    {"kana":"だいがく","kanji":"大学","meaning":"university"},
    {"kana":"びょういん","kanji":"病院","meaning":"hospital"},
    {"kana":"でんき","kanji":"電気","meaning":"electricity"},
    {"kana":"だれ","kanji":"誰","meaning":"who"},
    {"kana":"どなた","kanji":"どなた","meaning":"who (polite)"},
    {"kana":"〜さい","kanji":"〜歳","meaning":"years old"},
    {"kana":"なんさい","kanji":"何歳","meaning":"how old"},
    {"kana":"おいくつ","kanji":"おいくつ","meaning":"how old (polite)"},
    {"kana":"はい","kanji":"はい","meaning":"yes"},
    {"kana":"いいえ","kanji":"いいえ","meaning":"no"},
    {"kana":"しつれいですが","kanji":"失礼ですが","meaning":"excuse me but"},
    {"kana":"おなまえは","kanji":"お名前は","meaning":"may I have your name"},
    {"kana":"はじめまして","kanji":"初めまして","meaning":"how do you do"},
    {"kana":"どうぞよろしく","kanji":"どうぞよろしく","meaning":"pleased to meet you"},
    {"kana":"こちらは〜さんです","kanji":"こちらは〜さんです","meaning":"this is Mr./Ms.~"},
    {"kana":"〜からきました","kanji":"〜から来ました","meaning":"I came from ~"}
  ]
},

{
  "lesson": 2,
  "words": [
    {"kana":"これ","kanji":"これ","meaning":"this (thing near the speaker)"},
    {"kana":"それ","kanji":"それ","meaning":"that (thing near the listener)"},
    {"kana":"あれ","kanji":"あれ","meaning":"that (thing far from both)"},
    {"kana":"この","kanji":"この","meaning":"this ~"},
    {"kana":"その","kanji":"その","meaning":"that ~ near you"},
    {"kana":"あの","kanji":"あの","meaning":"that ~ over there"},
    {"kana":"ほん","kanji":"本","meaning":"book"},
    {"kana":"じしょ","kanji":"辞書","meaning":"dictionary"},
    {"kana":"ざっし","kanji":"雑誌","meaning":"magazine"},
    {"kana":"しんぶん","kanji":"新聞","meaning":"newspaper"},
    {"kana":"ノート","kanji":"ノート","meaning":"notebook"},
    {"kana":"てちょう","kanji":"手帳","meaning":"pocket notebook"},
    {"kana":"めいし","kanji":"名刺","meaning":"business card"},
    {"kana":"カード","kanji":"カード","meaning":"card"},
    {"kana":"テレホンカード","kanji":"テレホンカード","meaning":"telephone card"},
    {"kana":"えんぴつ","kanji":"鉛筆","meaning":"pencil"},
    {"kana":"ボールペン","kanji":"ボールペン","meaning":"ballpoint pen"},
    {"kana":"シャープペンシル","kanji":"シャープペンシル","meaning":"mechanical pencil"},
    {"kana":"かぎ","kanji":"鍵","meaning":"key"},
    {"kana":"とけい","kanji":"時計","meaning":"watch, clock"},
    {"kana":"かさ","kanji":"傘","meaning":"umbrella"},
    {"kana":"かばん","kanji":"鞄","meaning":"bag, briefcase"},
    {"kana":"カセットテープ","kanji":"カセットテープ","meaning":"cassette tape"},
    {"kana":"テープレコーダー","kanji":"テープレコーダー","meaning":"tape recorder"},
    {"kana":"テレビ","kanji":"テレビ","meaning":"television"},
    {"kana":"ラジオ","kanji":"ラジオ","meaning":"radio"},
    {"kana":"カメラ","kanji":"カメラ","meaning":"camera"},
    {"kana":"コンピューター","kanji":"コンピューター","meaning":"computer"},
    {"kana":"じどうしゃ","kanji":"自動車","meaning":"automobile, car"},
    {"kana":"つくえ","kanji":"机","meaning":"desk"},
    {"kana":"いす","kanji":"椅子","meaning":"chair"},
    {"kana":"チョコレート","kanji":"チョコレート","meaning":"chocolate"},
    {"kana":"コーヒー","kanji":"コーヒー","meaning":"coffee"},
    {"kana":"えいご","kanji":"英語","meaning":"English language"},
    {"kana":"にほんご","kanji":"日本語","meaning":"Japanese language"},
    {"kana":"〜ご","kanji":"〜語","meaning":"~ language"},
    {"kana":"なん","kanji":"何","meaning":"what"},
    {"kana":"そう","kanji":"そう","meaning":"so"},
    {"kana":"ちがいます","kanji":"違います","meaning":"No it isn't / You are wrong"},
    {"kana":"そうですか","kanji":"そうですか","meaning":"I see / Is that so"},
    {"kana":"あのう","kanji":"あのう","meaning":"well (hesitation)"},
    {"kana":"ほんのきもちです","kanji":"ほんの気持ちです","meaning":"It's nothing / token of gratitude"},
    {"kana":"どうぞ","kanji":"どうぞ","meaning":"please / here you are"},
    {"kana":"どうも","kanji":"どうも","meaning":"well thanks"},
    {"kana":"ありがとうございます","kanji":"ありがとうございます","meaning":"thank you very much"},
    {"kana":"こちらこそよろしく","kanji":"こちらこそよろしく","meaning":"I am pleased to meet you"}
  ]
},

{
  "lesson": 3,
  "words": [
    {"kana":"ここ","kanji":"ここ","meaning":"here, this place"},
    {"kana":"そこ","kanji":"そこ","meaning":"there, that place near you"},
    {"kana":"あそこ","kanji":"あそこ","meaning":"that place over there"},
    {"kana":"どこ","kanji":"どこ","meaning":"where"},
    {"kana":"こちら","kanji":"こちら","meaning":"this way, this place (polite)"},
    {"kana":"そちら","kanji":"そちら","meaning":"that way, that place near you (polite)"},
    {"kana":"あちら","kanji":"あちら","meaning":"that way, that place over there (polite)"},
    {"kana":"どちら","kanji":"どちら","meaning":"which way, where (polite)"},
    {"kana":"きょうしつ","kanji":"教室","meaning":"classroom"},
    {"kana":"しょくどう","kanji":"食堂","meaning":"dining hall, canteen"},
    {"kana":"じむしょ","kanji":"事務所","meaning":"office"},
    {"kana":"かいぎしつ","kanji":"会議室","meaning":"conference room"},
    {"kana":"うけつけ","kanji":"受付","meaning":"reception desk"},
    {"kana":"ロビー","kanji":"ロビー","meaning":"lobby"},
    {"kana":"へや","kanji":"部屋","meaning":"room"},
    {"kana":"トイレ","kanji":"トイレ","meaning":"toilet"},
    {"kana":"かいだん","kanji":"階段","meaning":"staircase"},
    {"kana":"エレベーター","kanji":"エレベーター","meaning":"elevator"},
    {"kana":"エスカレーター","kanji":"エスカレーター","meaning":"escalator"},
    {"kana":"くに","kanji":"国","meaning":"country"},
    {"kana":"うち","kanji":"家","meaning":"house, home"},
    {"kana":"でんわ","kanji":"電話","meaning":"telephone"},
    {"kana":"くつ","kanji":"靴","meaning":"shoes"},
    {"kana":"ネクタイ","kanji":"ネクタイ","meaning":"necktie"},
    {"kana":"ワイン","kanji":"ワイン","meaning":"wine"},
    {"kana":"たばこ","kanji":"煙草","meaning":"tobacco, cigarette"},
    {"kana":"うりば","kanji":"売り場","meaning":"department counter"},
    {"kana":"ちか","kanji":"地下","meaning":"basement"},
    {"kana":"〜かい","kanji":"〜階","meaning":"~th floor"},
    {"kana":"なんがい","kanji":"何階","meaning":"what floor"},
    {"kana":"〜えん","kanji":"〜円","meaning":"~yen"},
    {"kana":"いくら","kanji":"いくら","meaning":"how much"},
    {"kana":"ひゃく","kanji":"百","meaning":"hundred"},
    {"kana":"せん","kanji":"千","meaning":"thousand"},
    {"kana":"まん","kanji":"万","meaning":"ten thousand"},
    {"kana":"すみません","kanji":"すみません","meaning":"excuse me"},
    {"kana":"〜でございます","kanji":"〜でございます","meaning":"polite equivalent of です"},
    {"kana":"みせてください","kanji":"見せてください","meaning":"please show me"},
    {"kana":"じゃ","kanji":"じゃ","meaning":"well then"},
    {"kana":"ください","kanji":"ください","meaning":"please give me"}
  ]
},

{
  "lesson": 4,
  "words": [
    {"kana":"おきます","kanji":"起きます","meaning":"get up, wake up"},
    {"kana":"ねます","kanji":"寝ます","meaning":"sleep, go to bed"},
    {"kana":"はたらきます","kanji":"働きます","meaning":"work"},
    {"kana":"やすみます","kanji":"休みます","meaning":"take a rest, take a holiday"},
    {"kana":"べんきょうします","kanji":"勉強します","meaning":"study"},
    {"kana":"おわります","kanji":"終わります","meaning":"finish"},
    {"kana":"デパート","kanji":"デパート","meaning":"department store"},
    {"kana":"ぎんこう","kanji":"銀行","meaning":"bank"},
    {"kana":"ゆうびんきょく","kanji":"郵便局","meaning":"post office"},
    {"kana":"としょかん","kanji":"図書館","meaning":"library"},
    {"kana":"びじゅつかん","kanji":"美術館","meaning":"art museum"},
    {"kana":"いま","kanji":"今","meaning":"now"},
    {"kana":"〜じ","kanji":"〜時","meaning":"~ o'clock"},
    {"kana":"〜ふん","kanji":"〜分","meaning":"~ minute"},
    {"kana":"はん","kanji":"半","meaning":"half"},
    {"kana":"なんじ","kanji":"何時","meaning":"what time"},
    {"kana":"なんぷん","kanji":"何分","meaning":"what minute"},
    {"kana":"ごぜん","kanji":"午前","meaning":"a.m., morning"},
    {"kana":"ごご","kanji":"午後","meaning":"p.m., afternoon"},
    {"kana":"あさ","kanji":"朝","meaning":"morning"},
    {"kana":"ひる","kanji":"昼","meaning":"daytime, noon"},
    {"kana":"ばん","kanji":"晩","meaning":"night, evening"},
    {"kana":"おととい","kanji":"一昨日","meaning":"the day before yesterday"},
    {"kana":"きのう","kanji":"昨日","meaning":"yesterday"},
    {"kana":"きょう","kanji":"今日","meaning":"today"},
    {"kana":"あした","kanji":"明日","meaning":"tomorrow"},
    {"kana":"あさって","kanji":"明後日","meaning":"the day after tomorrow"},
    {"kana":"けさ","kanji":"今朝","meaning":"this morning"},
    {"kana":"こんばん","kanji":"今晩","meaning":"this evening, tonight"},
    {"kana":"やすみ","kanji":"休み","meaning":"holiday, day off"},
    {"kana":"ひるやすみ","kanji":"昼休み","meaning":"lunchtime"},
    {"kana":"まいあさ","kanji":"毎朝","meaning":"every morning"},
    {"kana":"まいばん","kanji":"毎晩","meaning":"every evening"},
    {"kana":"まいにち","kanji":"毎日","meaning":"every day"},
    {"kana":"げつようび","kanji":"月曜日","meaning":"Monday"},
    {"kana":"かようび","kanji":"火曜日","meaning":"Tuesday"},
    {"kana":"すいようび","kanji":"水曜日","meaning":"Wednesday"},
    {"kana":"もくようび","kanji":"木曜日","meaning":"Thursday"},
    {"kana":"きんようび","kanji":"金曜日","meaning":"Friday"},
    {"kana":"どようび","kanji":"土曜日","meaning":"Saturday"},
    {"kana":"にちようび","kanji":"日曜日","meaning":"Sunday"},
    {"kana":"なんようび","kanji":"何曜日","meaning":"what day of the week"},
    {"kana":"ばんごう","kanji":"番号","meaning":"number"},
    {"kana":"なんばん","kanji":"何番","meaning":"what number"},
    {"kana":"〜から","kanji":"〜から","meaning":"from ~"},
    {"kana":"〜まで","kanji":"〜まで","meaning":"until ~"},
    {"kana":"〜と〜","kanji":"〜と〜","meaning":"and (connecting nouns)"},
    {"kana":"たいへんですね","kanji":"大変ですね","meaning":"That's tough, isn't it"},
    {"kana":"あんない","kanji":"案内","meaning":"information, directory assistance"},
    {"kana":"おねがいします","kanji":"お願いします","meaning":"please (request)"},
    {"kana":"かしこまりました","kanji":"かしこまりました","meaning":"certainly"},
    {"kana":"おといあわせのばんごう","kanji":"お問い合わせの番号","meaning":"number being inquired about"},
    {"kana":"どうもありがとうございます","kanji":"どうもありがとうございます","meaning":"thank you very much"}
  ]
},

{
  "lesson": 5,
  "words": [
    {"kana":"いきます","kanji":"行きます","meaning":"go"},
    {"kana":"きます","kanji":"来ます","meaning":"come"},
    {"kana":"かえります","kanji":"帰ります","meaning":"go home, return"},
    {"kana":"がっこう","kanji":"学校","meaning":"school"},
    {"kana":"スーパー","kanji":"スーパー","meaning":"supermarket"},
    {"kana":"えき","kanji":"駅","meaning":"station"},
    {"kana":"ひこうき","kanji":"飛行機","meaning":"airplane"},
    {"kana":"ふね","kanji":"船","meaning":"ship"},
    {"kana":"でんしゃ","kanji":"電車","meaning":"electric train"},
    {"kana":"ちかてつ","kanji":"地下鉄","meaning":"subway"},
    {"kana":"しんかんせん","kanji":"新幹線","meaning":"bullet train"},
    {"kana":"バス","kanji":"バス","meaning":"bus"},
    {"kana":"タクシー","kanji":"タクシー","meaning":"taxi"},
    {"kana":"じてんしゃ","kanji":"自転車","meaning":"bicycle"},
    {"kana":"あるいて","kanji":"歩いて","meaning":"on foot"},
    {"kana":"ひと","kanji":"人","meaning":"person"},
    {"kana":"ともだち","kanji":"友達","meaning":"friend"},
    {"kana":"かれ","kanji":"彼","meaning":"he, boyfriend"},
    {"kana":"かのじょ","kanji":"彼女","meaning":"she, girlfriend"},
    {"kana":"かぞく","kanji":"家族","meaning":"family"},
    {"kana":"ひとりで","kanji":"一人で","meaning":"alone"},
    {"kana":"せんしゅう","kanji":"先週","meaning":"last week"},
    {"kana":"こんしゅう","kanji":"今週","meaning":"this week"},
    {"kana":"らいしゅう","kanji":"来週","meaning":"next week"},
    {"kana":"せんげつ","kanji":"先月","meaning":"last month"},
    {"kana":"こんげつ","kanji":"今月","meaning":"this month"},
    {"kana":"らいげつ","kanji":"来月","meaning":"next month"},
    {"kana":"きょねん","kanji":"去年","meaning":"last year"},
    {"kana":"ことし","kanji":"今年","meaning":"this year"},
    {"kana":"らいねん","kanji":"来年","meaning":"next year"},
    {"kana":"〜がつ","kanji":"〜月","meaning":"~ month"},
    {"kana":"なんがつ","kanji":"何月","meaning":"what month"},
    {"kana":"ついたち","kanji":"一日","meaning":"first day of month"},
    {"kana":"ふつか","kanji":"二日","meaning":"second day"},
    {"kana":"みっか","kanji":"三日","meaning":"third day"},
    {"kana":"よっか","kanji":"四日","meaning":"fourth day"},
    {"kana":"いつか","kanji":"五日","meaning":"fifth day"},
    {"kana":"むいか","kanji":"六日","meaning":"sixth day"},
    {"kana":"なのか","kanji":"七日","meaning":"seventh day"},
    {"kana":"ようか","kanji":"八日","meaning":"eighth day"},
    {"kana":"ここのか","kanji":"九日","meaning":"ninth day"},
    {"kana":"とおか","kanji":"十日","meaning":"tenth day"},
    {"kana":"じゅうよっか","kanji":"十四日","meaning":"fourteenth day"},
    {"kana":"はつか","kanji":"二十日","meaning":"twentieth day"},
    {"kana":"にじゅうよっか","kanji":"二十四日","meaning":"twenty fourth day"},
    {"kana":"〜にち","kanji":"〜日","meaning":"~ day of month"},
    {"kana":"なんにち","kanji":"何日","meaning":"which day, how many days"},
    {"kana":"いつ","kanji":"いつ","meaning":"when"},
    {"kana":"たんじょうび","kanji":"誕生日","meaning":"birthday"},
    {"kana":"ふつう","kanji":"普通","meaning":"local train"},
    {"kana":"きゅうこう","kanji":"急行","meaning":"rapid"},
    {"kana":"とっきゅう","kanji":"特急","meaning":"express"},
    {"kana":"つぎ","kanji":"次","meaning":"next"},
    {"kana":"どういたしまして","kanji":"どういたしまして","meaning":"you're welcome"},
    {"kana":"〜ばんせん","kanji":"〜番線","meaning":"platform number"}
  ]
},

{
  "lesson": 6,
  "words": [
    {"kana":"たべます","kanji":"食べます","meaning":"eat"},
    {"kana":"のみます","kanji":"飲みます","meaning":"drink"},
    {"kana":"すいます","kanji":"吸います","meaning":"smoke"},
    {"kana":"みます","kanji":"見ます","meaning":"see, watch, look"},
    {"kana":"ききます","kanji":"聞きます","meaning":"hear, listen"},
    {"kana":"よみます","kanji":"読みます","meaning":"read"},
    {"kana":"かきます","kanji":"書きます","meaning":"write, draw"},
    {"kana":"かいます","kanji":"買います","meaning":"buy"},
    {"kana":"とります","kanji":"撮ります","meaning":"take a photograph"},
    {"kana":"します","kanji":"します","meaning":"do"},
    {"kana":"あいます","kanji":"会います","meaning":"meet"},
    {"kana":"ごはん","kanji":"ご飯","meaning":"meal, cooked rice"},
    {"kana":"あさごはん","kanji":"朝ご飯","meaning":"breakfast"},
    {"kana":"ひるごはん","kanji":"昼ご飯","meaning":"lunch"},
    {"kana":"ばんごはん","kanji":"晩ご飯","meaning":"dinner"},
    {"kana":"パン","kanji":"パン","meaning":"bread"},
    {"kana":"たまご","kanji":"卵","meaning":"egg"},
    {"kana":"にく","kanji":"肉","meaning":"meat"},
    {"kana":"さかな","kanji":"魚","meaning":"fish"},
    {"kana":"やさい","kanji":"野菜","meaning":"vegetable"},
    {"kana":"くだもの","kanji":"果物","meaning":"fruit"},
    {"kana":"みず","kanji":"水","meaning":"water"},
    {"kana":"おちゃ","kanji":"お茶","meaning":"tea, green tea"},
    {"kana":"こうちゃ","kanji":"紅茶","meaning":"black tea"},
    {"kana":"ぎゅうにゅう","kanji":"牛乳","meaning":"milk"},
    {"kana":"ジュース","kanji":"ジュース","meaning":"juice"},
    {"kana":"ビール","kanji":"ビール","meaning":"beer"},
    {"kana":"おさけ","kanji":"お酒","meaning":"alcohol, sake"},
    {"kana":"ビデオ","kanji":"ビデオ","meaning":"video"},
    {"kana":"えいが","kanji":"映画","meaning":"movie"},
    {"kana":"CD","kanji":"CD","meaning":"CD"},
    {"kana":"てがみ","kanji":"手紙","meaning":"letter"},
    {"kana":"レポート","kanji":"レポート","meaning":"report"},
    {"kana":"しゃしん","kanji":"写真","meaning":"photograph"},
    {"kana":"みせ","kanji":"店","meaning":"store, shop"},
    {"kana":"レストラン","kanji":"レストラン","meaning":"restaurant"},
    {"kana":"にわ","kanji":"庭","meaning":"garden"},
    {"kana":"しゅくだい","kanji":"宿題","meaning":"homework"},
    {"kana":"テニス","kanji":"テニス","meaning":"tennis"},
    {"kana":"サッカー","kanji":"サッカー","meaning":"soccer"},
    {"kana":"おはなみ","kanji":"お花見","meaning":"cherry blossom viewing"},
    {"kana":"なに","kanji":"何","meaning":"what"},
    {"kana":"いっしょに","kanji":"一緒に","meaning":"together"},
    {"kana":"ちょっと","kanji":"ちょっと","meaning":"a little"},
    {"kana":"いつも","kanji":"いつも","meaning":"always"},
    {"kana":"ときどき","kanji":"時々","meaning":"sometimes"},
    {"kana":"それから","kanji":"それから","meaning":"after that"},
    {"kana":"ええ","kanji":"ええ","meaning":"yes"},
    {"kana":"いいですね","kanji":"いいですね","meaning":"that sounds good"},
    {"kana":"わかりました","kanji":"分かりました","meaning":"I see"},
    {"kana":"じゃ、また","kanji":"じゃ、また","meaning":"see you later"}
  ]
},

{
  "lesson": 7,
  "words": [
    {"kana":"きります","kanji":"切ります","meaning":"cut, slice"},
    {"kana":"おくります","kanji":"送ります","meaning":"send"},
    {"kana":"あげます","kanji":"あげます","meaning":"give"},
    {"kana":"もらいます","kanji":"もらいます","meaning":"receive"},
    {"kana":"かします","kanji":"貸します","meaning":"lend"},
    {"kana":"かります","kanji":"借ります","meaning":"borrow"},
    {"kana":"おしえます","kanji":"教えます","meaning":"teach"},
    {"kana":"ならいます","kanji":"習います","meaning":"learn"},
    {"kana":"かけます","kanji":"かけます","meaning":"make a telephone call"},
    {"kana":"て","kanji":"手","meaning":"hand"},
    {"kana":"はし","kanji":"箸","meaning":"chopsticks"},
    {"kana":"スプーン","kanji":"スプーン","meaning":"spoon"},
    {"kana":"ナイフ","kanji":"ナイフ","meaning":"knife"},
    {"kana":"フォーク","kanji":"フォーク","meaning":"fork"},
    {"kana":"はさみ","kanji":"鋏","meaning":"scissors"},
    {"kana":"ファックス","kanji":"ファックス","meaning":"fax"},
    {"kana":"ワープロ","kanji":"ワープロ","meaning":"word processor"},
    {"kana":"パソコン","kanji":"パソコン","meaning":"personal computer"},
    {"kana":"パンチ","kanji":"パンチ","meaning":"hole punch"},
    {"kana":"ホッチキス","kanji":"ホッチキス","meaning":"stapler"},
    {"kana":"セロテープ","kanji":"セロテープ","meaning":"scotch tape"},
    {"kana":"けしゴム","kanji":"消しゴム","meaning":"eraser"},
    {"kana":"かみ","kanji":"紙","meaning":"paper"},
    {"kana":"はな","kanji":"花","meaning":"flower"},
    {"kana":"シャツ","kanji":"シャツ","meaning":"shirt"},
    {"kana":"プレゼント","kanji":"プレゼント","meaning":"present, gift"},
    {"kana":"にもつ","kanji":"荷物","meaning":"baggage, parcel"},
    {"kana":"おかね","kanji":"お金","meaning":"money"},
    {"kana":"きっぷ","kanji":"切符","meaning":"ticket"},
    {"kana":"クリスマス","kanji":"クリスマス","meaning":"Christmas"},
    {"kana":"ちち","kanji":"父","meaning":"my father"},
    {"kana":"はは","kanji":"母","meaning":"my mother"},
    {"kana":"おとうさん","kanji":"お父さん","meaning":"someone else's father"},
    {"kana":"おかあさん","kanji":"お母さん","meaning":"someone else's mother"},
    {"kana":"もう","kanji":"もう","meaning":"already"},
    {"kana":"まだ","kanji":"まだ","meaning":"not yet"},
    {"kana":"これから","kanji":"これから","meaning":"from now on"},
    {"kana":"すてきですね","kanji":"素敵ですね","meaning":"what a nice ~"},
    {"kana":"いらっしゃい","kanji":"いらっしゃい","meaning":"welcome (visitor greeting)"},
    {"kana":"どうぞおあがりください","kanji":"どうぞお上がりください","meaning":"please come in"},
    {"kana":"おじゃまします","kanji":"お邪魔します","meaning":"thank you for having me"},
    {"kana":"いかがですか","kanji":"いかがですか","meaning":"would you like ~"},
    {"kana":"いただきます","kanji":"いただきます","meaning":"said before eating or drinking"},
    {"kana":"りょこう","kanji":"旅行","meaning":"trip, travel"},
    {"kana":"おみやげ","kanji":"お土産","meaning":"souvenir"}
  ]
},

{
  "lesson": 8,
  "words": [
    {"kana":"ハンサム","kanji":"ハンサム","meaning":"handsome"},
    {"kana":"きれい","kanji":"綺麗","meaning":"beautiful, clean"},
    {"kana":"しずか","kanji":"静か","meaning":"quiet"},
    {"kana":"にぎやか","kanji":"賑やか","meaning":"lively"},
    {"kana":"ゆうめい","kanji":"有名","meaning":"famous"},
    {"kana":"しんせつ","kanji":"親切","meaning":"kind"},
    {"kana":"げんき","kanji":"元気","meaning":"healthy, cheerful"},
    {"kana":"ひま","kanji":"暇","meaning":"free time"},
    {"kana":"べんり","kanji":"便利","meaning":"convenient"},
    {"kana":"すてき","kanji":"素敵","meaning":"fine, nice"},
    {"kana":"おおきい","kanji":"大きい","meaning":"big"},
    {"kana":"ちいさい","kanji":"小さい","meaning":"small"},
    {"kana":"あたらしい","kanji":"新しい","meaning":"new"},
    {"kana":"ふるい","kanji":"古い","meaning":"old (object)"},
    {"kana":"いい","kanji":"良い","meaning":"good"},
    {"kana":"わるい","kanji":"悪い","meaning":"bad"},
    {"kana":"あつい","kanji":"暑い","meaning":"hot (weather)"},
    {"kana":"さむい","kanji":"寒い","meaning":"cold (weather)"},
    {"kana":"つめたい","kanji":"冷たい","meaning":"cold (touch, drink)"},
    {"kana":"むずかしい","kanji":"難しい","meaning":"difficult"},
    {"kana":"やさしい","kanji":"易しい","meaning":"easy"},
    {"kana":"たかい","kanji":"高い","meaning":"expensive, tall"},
    {"kana":"やすい","kanji":"安い","meaning":"cheap"},
    {"kana":"ひくい","kanji":"低い","meaning":"low"},
    {"kana":"おもしろい","kanji":"面白い","meaning":"interesting"},
    {"kana":"おいしい","kanji":"美味しい","meaning":"delicious"},
    {"kana":"いそがしい","kanji":"忙しい","meaning":"busy"},
    {"kana":"たのしい","kanji":"楽しい","meaning":"enjoyable"},
    {"kana":"しろい","kanji":"白い","meaning":"white"},
    {"kana":"くろい","kanji":"黒い","meaning":"black"},
    {"kana":"あかい","kanji":"赤い","meaning":"red"},
    {"kana":"あおい","kanji":"青い","meaning":"blue"},
    {"kana":"さくら","kanji":"桜","meaning":"cherry blossom"},
    {"kana":"やま","kanji":"山","meaning":"mountain"},
    {"kana":"まち","kanji":"町","meaning":"town, city"},
    {"kana":"たべもの","kanji":"食べ物","meaning":"food"},
    {"kana":"くるま","kanji":"車","meaning":"car"},
    {"kana":"ところ","kanji":"所","meaning":"place"},
    {"kana":"りょう","kanji":"寮","meaning":"dormitory"},
    {"kana":"べんきょう","kanji":"勉強","meaning":"study"},
    {"kana":"せいかつ","kanji":"生活","meaning":"life"},
    {"kana":"しごと","kanji":"仕事","meaning":"work"},
    {"kana":"どう","kanji":"どう","meaning":"how"},
    {"kana":"どんな","kanji":"どんな","meaning":"what kind of"},
    {"kana":"どれ","kanji":"どれ","meaning":"which one"},
    {"kana":"とても","kanji":"とても","meaning":"very"},
    {"kana":"あまり","kanji":"あまり","meaning":"not so"},
    {"kana":"そして","kanji":"そして","meaning":"and"},
    {"kana":"でも","kanji":"でも","meaning":"but"},
    {"kana":"おげんきですか","kanji":"お元気ですか","meaning":"how are you"},
    {"kana":"そうですね","kanji":"そうですね","meaning":"well let me see"},
    {"kana":"にほんのせいかつになれましたか","kanji":"日本の生活に慣れましたか","meaning":"have you got used to life in Japan"},
    {"kana":"もういっぱいいかがですか","kanji":"もう一杯いかがですか","meaning":"won't you have another cup"},
    {"kana":"いいえ、けっこうです","kanji":"いいえ、結構です","meaning":"no thank you"},
    {"kana":"もう〜ですね","kanji":"もう〜ですね","meaning":"it's already ~"},
    {"kana":"そろそろしつれいします","kanji":"そろそろ失礼します","meaning":"it's almost time to leave"},
    {"kana":"またいらっしゃってください","kanji":"またいらっしゃってください","meaning":"please come again"}
  ]
},

{
  "lesson": 9,
  "words": [
    {"kana":"わかります","kanji":"分かります","meaning":"understand"},
    {"kana":"あります","kanji":"あります","meaning":"have"},
    {"kana":"すき","kanji":"好き","meaning":"like"},
    {"kana":"きらい","kanji":"嫌い","meaning":"dislike"},
    {"kana":"じょうず","kanji":"上手","meaning":"good at"},
    {"kana":"へた","kanji":"下手","meaning":"poor at"},
    {"kana":"りょうり","kanji":"料理","meaning":"dish, cooking"},
    {"kana":"のみもの","kanji":"飲み物","meaning":"drink"},
    {"kana":"スポーツ","kanji":"スポーツ","meaning":"sports"},
    {"kana":"やきゅう","kanji":"野球","meaning":"baseball"},
    {"kana":"ダンス","kanji":"ダンス","meaning":"dance"},
    {"kana":"おんがく","kanji":"音楽","meaning":"music"},
    {"kana":"うた","kanji":"歌","meaning":"song"},
    {"kana":"クラシック","kanji":"クラシック","meaning":"classical music"},
    {"kana":"ジャズ","kanji":"ジャズ","meaning":"jazz"},
    {"kana":"コンサート","kanji":"コンサート","meaning":"concert"},
    {"kana":"カラオケ","kanji":"カラオケ","meaning":"karaoke"},
    {"kana":"かぶき","kanji":"歌舞伎","meaning":"kabuki"},
    {"kana":"え","kanji":"絵","meaning":"picture, drawing"},
    {"kana":"じ","kanji":"字","meaning":"letter, character"},
    {"kana":"かんじ","kanji":"漢字","meaning":"Chinese character"},
    {"kana":"ひらがな","kanji":"ひらがな","meaning":"hiragana"},
    {"kana":"カタカナ","kanji":"カタカナ","meaning":"katakana"},
    {"kana":"ローマじ","kanji":"ローマ字","meaning":"Roman alphabet"},
    {"kana":"こまかいおかね","kanji":"細かいお金","meaning":"small change"},
    {"kana":"きっぷ","kanji":"切符","meaning":"ticket"},
    {"kana":"じかん","kanji":"時間","meaning":"time"},
    {"kana":"ようじ","kanji":"用事","meaning":"something to do, errand"},
    {"kana":"やくそく","kanji":"約束","meaning":"appointment, promise"},
    {"kana":"ごしゅじん","kanji":"ご主人","meaning":"someone else's husband"},
    {"kana":"おっと","kanji":"夫","meaning":"my husband"},
    {"kana":"おくさん","kanji":"奥さん","meaning":"someone else's wife"},
    {"kana":"つま","kanji":"妻","meaning":"my wife"},
    {"kana":"こども","kanji":"子供","meaning":"child"},
    {"kana":"よく","kanji":"よく","meaning":"well, much"},
    {"kana":"だいたい","kanji":"大体","meaning":"mostly, roughly"},
    {"kana":"たくさん","kanji":"沢山","meaning":"many, much"},
    {"kana":"すこし","kanji":"少し","meaning":"a little"},
    {"kana":"ぜんぜん","kanji":"全然","meaning":"not at all"},
    {"kana":"はやく","kanji":"早く","meaning":"early, quickly"},
    {"kana":"〜から","kanji":"〜から","meaning":"because"},
    {"kana":"どうして","kanji":"どうして","meaning":"why"},
    {"kana":"ざんねんですね","kanji":"残念ですね","meaning":"that's a pity"},
    {"kana":"すみません","kanji":"すみません","meaning":"I am sorry"},
    {"kana":"もしもし","kanji":"もしもし","meaning":"hello (on phone)"},
    {"kana":"ああ","kanji":"ああ","meaning":"oh"},
    {"kana":"いっしょにいかがですか","kanji":"一緒にいかがですか","meaning":"won't you join me"},
    {"kana":"ちょっとむずかしいです","kanji":"ちょっと難しいです","meaning":"it's a bit difficult"},
    {"kana":"そうですか","kanji":"そうですか","meaning":"so you cannot"}
  ]
},

{
  "lesson": 10,
  "words": [
    {"kana":"います","kanji":"います","meaning":"exist, be (animate things)"},
    {"kana":"あります","kanji":"あります","meaning":"exist, be (inanimate things)"},
    {"kana":"いろいろ","kanji":"色々","meaning":"various"},
    {"kana":"おとこのひと","kanji":"男の人","meaning":"man"},
    {"kana":"おんなのひと","kanji":"女の人","meaning":"woman"},
    {"kana":"おとこのこ","kanji":"男の子","meaning":"boy"},
    {"kana":"おんなのこ","kanji":"女の子","meaning":"girl"},
    {"kana":"いぬ","kanji":"犬","meaning":"dog"},
    {"kana":"ねこ","kanji":"猫","meaning":"cat"},
    {"kana":"き","kanji":"木","meaning":"tree"},
    {"kana":"もの","kanji":"物","meaning":"thing"},
    {"kana":"フィルム","kanji":"フィルム","meaning":"film"},
    {"kana":"でんち","kanji":"電池","meaning":"battery"},
    {"kana":"はこ","kanji":"箱","meaning":"box"},
    {"kana":"スイッチ","kanji":"スイッチ","meaning":"switch"},
    {"kana":"れいぞうこ","kanji":"冷蔵庫","meaning":"refrigerator"},
    {"kana":"テーブル","kanji":"テーブル","meaning":"table"},
    {"kana":"ベッド","kanji":"ベッド","meaning":"bed"},
    {"kana":"たな","kanji":"棚","meaning":"shelf"},
    {"kana":"ドア","kanji":"ドア","meaning":"door"},
    {"kana":"まど","kanji":"窓","meaning":"window"},
    {"kana":"ポスト","kanji":"ポスト","meaning":"mailbox"},
    {"kana":"たてもの","kanji":"建物","meaning":"building"},
    {"kana":"こうえん","kanji":"公園","meaning":"park"},
    {"kana":"きっさてん","kanji":"喫茶店","meaning":"coffee shop"},
    {"kana":"ほんや","kanji":"本屋","meaning":"bookstore"},
    {"kana":"〜や","kanji":"〜屋","meaning":"~ store"},
    {"kana":"のりば","kanji":"乗り場","meaning":"transport stop"},
    {"kana":"けん","kanji":"県","meaning":"prefecture"},
    {"kana":"うえ","kanji":"上","meaning":"on, above"},
    {"kana":"した","kanji":"下","meaning":"under"},
    {"kana":"まえ","kanji":"前","meaning":"front"},
    {"kana":"うしろ","kanji":"後ろ","meaning":"behind"},
    {"kana":"みぎ","kanji":"右","meaning":"right"},
    {"kana":"ひだり","kanji":"左","meaning":"left"},
    {"kana":"なか","kanji":"中","meaning":"inside"},
    {"kana":"そと","kanji":"外","meaning":"outside"},
    {"kana":"となり","kanji":"隣","meaning":"next to"},
    {"kana":"ちかく","kanji":"近く","meaning":"near"},
    {"kana":"あいだ","kanji":"間","meaning":"between"},
    {"kana":"〜など","kanji":"〜など","meaning":"~ etc"},
    {"kana":"いちばん","kanji":"一番","meaning":"the most"},
    {"kana":"〜だんめ","kanji":"〜段目","meaning":"~th shelf"},
    {"kana":"チリソース","kanji":"チリソース","meaning":"chili sauce"},
    {"kana":"おく","kanji":"奥","meaning":"back"},
    {"kana":"スパイスコーナー","kanji":"スパイスコーナー","meaning":"spice corner"}
  ]
},

{
  "lesson": 11,
  "words": [
    {"kana":"こどもがいます","kanji":"子供がいます","meaning":"have a child"},
    {"kana":"にほんにいます","kanji":"日本にいます","meaning":"stay in Japan"},
    {"kana":"やすみます","kanji":"休みます","meaning":"take a day off"},
    {"kana":"〜こ","kanji":"〜個","meaning":"counter for things"},
    {"kana":"いくつ","kanji":"幾つ","meaning":"how many"},
    {"kana":"ひとり","kanji":"一人","meaning":"one person"},
    {"kana":"ふたり","kanji":"二人","meaning":"two people"},
    {"kana":"〜にん","kanji":"〜人","meaning":"people counter"},
    {"kana":"〜だい","kanji":"〜台","meaning":"counter for machines, cars"},
    {"kana":"〜まい","kanji":"〜枚","meaning":"counter for flat objects"},
    {"kana":"〜かい","kanji":"〜回","meaning":"~ times"},
    {"kana":"りんご","kanji":"林檎","meaning":"apple"},
    {"kana":"みかん","kanji":"蜜柑","meaning":"mandarin orange"},
    {"kana":"サンドイッチ","kanji":"サンドイッチ","meaning":"sandwich"},
    {"kana":"カレーライス","kanji":"カレーライス","meaning":"curry rice"},
    {"kana":"アイスクリーム","kanji":"アイスクリーム","meaning":"ice cream"},
    {"kana":"きって","kanji":"切手","meaning":"postage stamp"},
    {"kana":"はがき","kanji":"葉書","meaning":"postcard"},
    {"kana":"ふうとう","kanji":"封筒","meaning":"envelope"},
    {"kana":"そくたつ","kanji":"速達","meaning":"special delivery"},
    {"kana":"かきとめ","kanji":"書留","meaning":"registered mail"},
    {"kana":"こうくうびん","kanji":"航空便","meaning":"airmail"},
    {"kana":"ふなびん","kanji":"船便","meaning":"sea mail"},
    {"kana":"りょうしん","kanji":"両親","meaning":"parents"},
    {"kana":"きょうだい","kanji":"兄弟","meaning":"brothers and sisters"},
    {"kana":"あに","kanji":"兄","meaning":"my elder brother"},
    {"kana":"おにいさん","kanji":"お兄さん","meaning":"someone else's elder brother"},
    {"kana":"あね","kanji":"姉","meaning":"my elder sister"},
    {"kana":"おねえさん","kanji":"お姉さん","meaning":"someone else's elder sister"},
    {"kana":"おとうと","kanji":"弟","meaning":"my younger brother"},
    {"kana":"おとうとさん","kanji":"弟さん","meaning":"someone else's younger brother"},
    {"kana":"いもうと","kanji":"妹","meaning":"my younger sister"},
    {"kana":"いもうとさん","kanji":"妹さん","meaning":"someone else's younger sister"},
    {"kana":"がいこく","kanji":"外国","meaning":"foreign country"},
    {"kana":"〜じかん","kanji":"〜時間","meaning":"~ hours"},
    {"kana":"〜しゅうかん","kanji":"〜週間","meaning":"~ weeks"},
    {"kana":"〜かげつ","kanji":"〜ヶ月","meaning":"~ months"},
    {"kana":"〜ねん","kanji":"〜年","meaning":"~ years"},
    {"kana":"ぐらい","kanji":"ぐらい","meaning":"about"},
    {"kana":"どのくらい","kanji":"どのくらい","meaning":"how long"},
    {"kana":"ぜんぶで","kanji":"全部で","meaning":"in total"},
    {"kana":"みんな","kanji":"皆","meaning":"all"},
    {"kana":"だけ","kanji":"だけ","meaning":"only"},
    {"kana":"いらっしゃいませ","kanji":"いらっしゃいませ","meaning":"welcome (shop greeting)"},
    {"kana":"いいてんきですね","kanji":"いい天気ですね","meaning":"nice weather, isn't it"},
    {"kana":"でかけますか","kanji":"出かけますか","meaning":"are you going out"},
    {"kana":"ちょっと〜まで","kanji":"ちょっと〜まで","meaning":"I'm just going to ~"},
    {"kana":"いってきます","kanji":"行ってきます","meaning":"I'm going and coming back"},
    {"kana":"いってらっしゃい","kanji":"行ってらっしゃい","meaning":"please go and come back"}
  ]
},

{
  "lesson": 12,
  "words": [
    {"kana":"やさしい","kanji":"易しい","meaning":"easy, simple"},
    {"kana":"ちかい","kanji":"近い","meaning":"near"},
    {"kana":"とおい","kanji":"遠い","meaning":"far"},
    {"kana":"はやい","kanji":"速い","meaning":"fast, early"},
    {"kana":"おそい","kanji":"遅い","meaning":"slow, late"},
    {"kana":"おおい","kanji":"多い","meaning":"many, much"},
    {"kana":"すくない","kanji":"少ない","meaning":"few"},
    {"kana":"あたたかい","kanji":"暖かい","meaning":"warm"},
    {"kana":"すずしい","kanji":"涼しい","meaning":"cool"},
    {"kana":"あまい","kanji":"甘い","meaning":"sweet"},
    {"kana":"からい","kanji":"辛い","meaning":"spicy"},
    {"kana":"おもい","kanji":"重い","meaning":"heavy"},
    {"kana":"かるい","kanji":"軽い","meaning":"light"},
    {"kana":"コーヒーがすき","kanji":"コーヒーが好き","meaning":"prefer coffee"},
    {"kana":"きせつ","kanji":"季節","meaning":"season"},
    {"kana":"なつ","kanji":"夏","meaning":"summer"},
    {"kana":"あき","kanji":"秋","meaning":"autumn"},
    {"kana":"ふゆ","kanji":"冬","meaning":"winter"},
    {"kana":"てんき","kanji":"天気","meaning":"weather"},
    {"kana":"あめ","kanji":"雨","meaning":"rain"},
    {"kana":"ゆき","kanji":"雪","meaning":"snow"},
    {"kana":"くもり","kanji":"曇り","meaning":"cloudy"},
    {"kana":"ホテル","kanji":"ホテル","meaning":"hotel"},
    {"kana":"くうこう","kanji":"空港","meaning":"airport"},
    {"kana":"うみ","kanji":"海","meaning":"sea"},
    {"kana":"せかい","kanji":"世界","meaning":"world"},
    {"kana":"パーティー","kanji":"パーティー","meaning":"party"},
    {"kana":"まつり","kanji":"祭り","meaning":"festival"},
    {"kana":"しけん","kanji":"試験","meaning":"examination"},
    {"kana":"すきやき","kanji":"すき焼き","meaning":"sukiyaki"},
    {"kana":"さしみ","kanji":"刺身","meaning":"sashimi"},
    {"kana":"すし","kanji":"寿司","meaning":"sushi"},
    {"kana":"てんぷら","kanji":"天ぷら","meaning":"tempura"},
    {"kana":"いけばな","kanji":"生け花","meaning":"flower arrangement"},
    {"kana":"もみじ","kanji":"紅葉","meaning":"maple leaves"},
    {"kana":"どちら","kanji":"どちら","meaning":"which one (two)"},
    {"kana":"どちらも","kanji":"どちらも","meaning":"both"},
    {"kana":"ずっと","kanji":"ずっと","meaning":"by far"},
    {"kana":"はじめて","kanji":"初めて","meaning":"for the first time"},
    {"kana":"ただいま","kanji":"ただいま","meaning":"I'm home"},
    {"kana":"おかえりなさい","kanji":"お帰りなさい","meaning":"welcome home"},
    {"kana":"すごいですね","kanji":"すごいですね","meaning":"that's amazing"},
    {"kana":"つかれました","kanji":"疲れました","meaning":"I'm tired"}
  ]
},

{
  "lesson": 13,
  "words": [
    {"kana":"あそびます","kanji":"遊びます","meaning":"enjoy oneself, play"},
    {"kana":"およぎます","kanji":"泳ぎます","meaning":"swim"},
    {"kana":"むかえます","kanji":"迎えます","meaning":"go to meet, welcome"},
    {"kana":"つかれます","kanji":"疲れます","meaning":"get tired"},
    {"kana":"てがみをだします","kanji":"手紙を出します","meaning":"send a letter"},
    {"kana":"みせにはいります","kanji":"店に入ります","meaning":"enter a shop"},
    {"kana":"みせをでます","kanji":"店を出ます","meaning":"leave a shop"},
    {"kana":"けっこんします","kanji":"結婚します","meaning":"marry"},
    {"kana":"かいものします","kanji":"買い物します","meaning":"do shopping"},
    {"kana":"しょくじします","kanji":"食事します","meaning":"have a meal"},
    {"kana":"こうえんをさんぽします","kanji":"公園を散歩します","meaning":"take a walk in a park"},
    {"kana":"たいへん","kanji":"大変","meaning":"hard, tough"},
    {"kana":"ほしい","kanji":"欲しい","meaning":"want something"},
    {"kana":"さびしい","kanji":"寂しい","meaning":"lonely"},
    {"kana":"ひろい","kanji":"広い","meaning":"wide, spacious"},
    {"kana":"せまい","kanji":"狭い","meaning":"narrow"},
    {"kana":"しやくしょ","kanji":"市役所","meaning":"city hall"},
    {"kana":"プール","kanji":"プール","meaning":"swimming pool"},
    {"kana":"かわ","kanji":"川","meaning":"river"},
    {"kana":"けいざい","kanji":"経済","meaning":"economy"},
    {"kana":"びじゅつ","kanji":"美術","meaning":"fine arts"},
    {"kana":"つり","kanji":"釣り","meaning":"fishing"},
    {"kana":"スキー","kanji":"スキー","meaning":"skiing"},
    {"kana":"かいぎ","kanji":"会議","meaning":"meeting"},
    {"kana":"とうろく","kanji":"登録","meaning":"registration"},
    {"kana":"しゅうまつ","kanji":"週末","meaning":"weekend"},
    {"kana":"ごろ","kanji":"頃","meaning":"about (time)"},
    {"kana":"なにか","kanji":"何か","meaning":"something"},
    {"kana":"どこか","kanji":"どこか","meaning":"somewhere"},
    {"kana":"おなかがすきました","kanji":"お腹が空きました","meaning":"I'm hungry"},
    {"kana":"おなかがいっぱいです","kanji":"お腹がいっぱいです","meaning":"I'm full"},
    {"kana":"のどがかわきました","kanji":"喉が渇きました","meaning":"I'm thirsty"},
    {"kana":"そうですね","kanji":"そうですね","meaning":"I agree"},
    {"kana":"そうしましょう","kanji":"そうしましょう","meaning":"let's do that"},
    {"kana":"ごちゅうもんは","kanji":"ご注文は","meaning":"may I take your order"},
    {"kana":"ていしょく","kanji":"定食","meaning":"set meal"},
    {"kana":"ぎゅうどん","kanji":"牛丼","meaning":"bowl of rice with beef"},
    {"kana":"しょうしょうおまちください","kanji":"少々お待ちください","meaning":"please wait a moment"},
    {"kana":"べつべつに","kanji":"別々に","meaning":"separately"}
  ]
},

{
  "lesson": 14,
  "words": [
    {"kana":"つけます","kanji":"付けます","meaning":"turn on"},
    {"kana":"けします","kanji":"消します","meaning":"turn off"},
    {"kana":"あけます","kanji":"開けます","meaning":"open"},
    {"kana":"しめます","kanji":"閉めます","meaning":"close"},
    {"kana":"いそぎます","kanji":"急ぎます","meaning":"hurry"},
    {"kana":"まちます","kanji":"待ちます","meaning":"wait"},
    {"kana":"とめます","kanji":"止めます","meaning":"stop, park"},
    {"kana":"まがります","kanji":"曲がります","meaning":"turn"},
    {"kana":"もちます","kanji":"持ちます","meaning":"hold"},
    {"kana":"とります","kanji":"取ります","meaning":"take, pass"},
    {"kana":"てつだいます","kanji":"手伝います","meaning":"help"},
    {"kana":"よびます","kanji":"呼びます","meaning":"call"},
    {"kana":"はなします","kanji":"話します","meaning":"speak"},
    {"kana":"みせます","kanji":"見せます","meaning":"show"},
    {"kana":"おしえます","kanji":"教えます","meaning":"tell"},
    {"kana":"はじめます","kanji":"始めます","meaning":"start"},
    {"kana":"あめがふります","kanji":"雨が降ります","meaning":"rain"},
    {"kana":"コピーします","kanji":"コピーします","meaning":"copy"},
    {"kana":"エアコン","kanji":"エアコン","meaning":"air conditioner"},
    {"kana":"パスポート","kanji":"パスポート","meaning":"passport"},
    {"kana":"なまえ","kanji":"名前","meaning":"name"},
    {"kana":"じゅうしょ","kanji":"住所","meaning":"address"},
    {"kana":"ちず","kanji":"地図","meaning":"map"},
    {"kana":"しお","kanji":"塩","meaning":"salt"},
    {"kana":"さとう","kanji":"砂糖","meaning":"sugar"},
    {"kana":"よみかた","kanji":"読み方","meaning":"how to read"},
    {"kana":"やりかた","kanji":"やり方","meaning":"how to do"},
    {"kana":"ゆっくり","kanji":"ゆっくり","meaning":"slowly"},
    {"kana":"すぐに","kanji":"すぐに","meaning":"immediately"},
    {"kana":"また","kanji":"また","meaning":"again"},
    {"kana":"あとで","kanji":"後で","meaning":"later"},
    {"kana":"もうすこし","kanji":"もう少し","meaning":"a little more"},
    {"kana":"もう〜","kanji":"もう〜","meaning":"another ~"},
    {"kana":"もちろん","kanji":"もちろん","meaning":"certainly"},
    {"kana":"いいですよ","kanji":"いいですよ","meaning":"all right"},
    {"kana":"あっ","kanji":"あっ","meaning":"oh"},
    {"kana":"しんごうをみぎにまがります","kanji":"信号を右に曲がります","meaning":"turn right at the signal"},
    {"kana":"まっすぐ","kanji":"真っ直ぐ","meaning":"straight"},
    {"kana":"これでおねがいします","kanji":"これでお願いします","meaning":"I'd like to pay with this"},
    {"kana":"おつり","kanji":"お釣り","meaning":"change"}
  ]
},

{
  "lesson": 15,
  "words": [
    {"kana":"たちます","kanji":"立ちます","meaning":"stand up"},
    {"kana":"すわります","kanji":"座ります","meaning":"sit down"},
    {"kana":"つかいます","kanji":"使います","meaning":"use"},
    {"kana":"おきます","kanji":"置きます","meaning":"put"},
    {"kana":"つくります","kanji":"作ります","meaning":"make, produce"},
    {"kana":"うります","kanji":"売ります","meaning":"sell"},
    {"kana":"しります","kanji":"知ります","meaning":"get to know"},
    {"kana":"すみます","kanji":"住みます","meaning":"live"},
    {"kana":"けんきゅうします","kanji":"研究します","meaning":"do research"},
    {"kana":"しっています","kanji":"知っています","meaning":"know"},
    {"kana":"おおさかにすんでいます","kanji":"大阪に住んでいます","meaning":"live in Osaka"},
    {"kana":"しりょう","kanji":"資料","meaning":"materials"},
    {"kana":"カタログ","kanji":"カタログ","meaning":"catalog"},
    {"kana":"じこくひょう","kanji":"時刻表","meaning":"timetable"},
    {"kana":"ふく","kanji":"服","meaning":"clothes"},
    {"kana":"せいひん","kanji":"製品","meaning":"products"},
    {"kana":"ソフト","kanji":"ソフト","meaning":"software"},
    {"kana":"せんもん","kanji":"専門","meaning":"specialty, field of study"},
    {"kana":"しかい","kanji":"歯科医","meaning":"dentist"},
    {"kana":"とこや","kanji":"床屋","meaning":"barber"},
    {"kana":"チケットうりば","kanji":"チケット売り場","meaning":"ticket agency"},
    {"kana":"どくしん","kanji":"独身","meaning":"single, unmarried"},
    {"kana":"とくに","kanji":"特に","meaning":"especially"},
    {"kana":"おもいだします","kanji":"思い出します","meaning":"remember"},
    {"kana":"ごかぞく","kanji":"ご家族","meaning":"your family"},
    {"kana":"こうこう","kanji":"高校","meaning":"senior high school"}
  ]
},

{
  "lesson": 16,
  "words": [
    {"kana":"のります","kanji":"乗ります","meaning":"ride, get on"},
    {"kana":"おります","kanji":"降ります","meaning":"get off"},
    {"kana":"のりかえます","kanji":"乗り換えます","meaning":"change (trains etc)"},
    {"kana":"シャワーをあびます","kanji":"シャワーを浴びます","meaning":"take a shower"},
    {"kana":"いれます","kanji":"入れます","meaning":"put in, insert"},
    {"kana":"だします","kanji":"出します","meaning":"take out, withdraw"},
    {"kana":"だいがくにはいります","kanji":"大学に入ります","meaning":"enter university"},
    {"kana":"だいがくをそつぎょうします","kanji":"大学を卒業します","meaning":"graduate university"},
    {"kana":"やめます","kanji":"辞めます","meaning":"quit, retire"},
    {"kana":"おします","kanji":"押します","meaning":"press"},
    {"kana":"わかい","kanji":"若い","meaning":"young"},
    {"kana":"ながい","kanji":"長い","meaning":"long"},
    {"kana":"みじかい","kanji":"短い","meaning":"short"},
    {"kana":"あかるい","kanji":"明るい","meaning":"bright"},
    {"kana":"くらい","kanji":"暗い","meaning":"dark"},
    {"kana":"せがたかい","kanji":"背が高い","meaning":"tall"},
    {"kana":"あたまがいい","kanji":"頭がいい","meaning":"clever"},
    {"kana":"からだ","kanji":"体","meaning":"body"},
    {"kana":"あたま","kanji":"頭","meaning":"head"},
    {"kana":"かみ","kanji":"髪","meaning":"hair"},
    {"kana":"かお","kanji":"顔","meaning":"face"},
    {"kana":"め","kanji":"目","meaning":"eye"},
    {"kana":"みみ","kanji":"耳","meaning":"ear"},
    {"kana":"くち","kanji":"口","meaning":"mouth"},
    {"kana":"は","kanji":"歯","meaning":"tooth"},
    {"kana":"おなか","kanji":"お腹","meaning":"stomach"},
    {"kana":"あし","kanji":"足","meaning":"leg, foot"},
    {"kana":"サービス","kanji":"サービス","meaning":"service"},
    {"kana":"ジョギング","kanji":"ジョギング","meaning":"jogging"},
    {"kana":"シャワー","kanji":"シャワー","meaning":"shower"},
    {"kana":"みどり","kanji":"緑","meaning":"greenery"},
    {"kana":"おてら","kanji":"お寺","meaning":"Buddhist temple"},
    {"kana":"じんじゃ","kanji":"神社","meaning":"Shinto shrine"},
    {"kana":"りゅうがくせい","kanji":"留学生","meaning":"foreign student"},
    {"kana":"〜ばん","kanji":"〜番","meaning":"number ~"},
    {"kana":"どうやって","kanji":"どうやって","meaning":"in what way, how"},
    {"kana":"どれ","kanji":"どれ","meaning":"which (3 or more)"},
    {"kana":"まだまだです","kanji":"まだまだです","meaning":"I still have a long way to go"},
    {"kana":"おろしますか","kanji":"おろしますか","meaning":"are you making a withdrawal"},
    {"kana":"まず","kanji":"まず","meaning":"first of all"},
    {"kana":"キャッシュカード","kanji":"キャッシュカード","meaning":"cash card"},
    {"kana":"あんしょうばんごう","kanji":"暗証番号","meaning":"pin number"},
    {"kana":"つぎに","kanji":"次に","meaning":"next"},
    {"kana":"きんがく","kanji":"金額","meaning":"amount of money"},
    {"kana":"かくにん","kanji":"確認","meaning":"confirmation"},
    {"kana":"ボタン","kanji":"ボタン","meaning":"button"}
  ]
},

{
  "lesson": 17,
  "words": [
    {"kana":"おぼえます","kanji":"覚えます","meaning":"memorize"},
    {"kana":"わすれます","kanji":"忘れます","meaning":"forget"},
    {"kana":"なくします","kanji":"無くします","meaning":"lose"},
    {"kana":"だします","kanji":"出します","meaning":"hand in"},
    {"kana":"はらいます","kanji":"払います","meaning":"pay"},
    {"kana":"かえします","kanji":"返します","meaning":"return"},
    {"kana":"でかけます","kanji":"出かけます","meaning":"go out"},
    {"kana":"ぬぎます","kanji":"脱ぎます","meaning":"take off clothes"},
    {"kana":"もっていきます","kanji":"持って行きます","meaning":"take something"},
    {"kana":"もってきます","kanji":"持って来ます","meaning":"bring something"},
    {"kana":"しんぱいします","kanji":"心配します","meaning":"worry"},
    {"kana":"ざんぎょうします","kanji":"残業します","meaning":"work overtime"},
    {"kana":"しゅっちょうします","kanji":"出張します","meaning":"go on business trip"},
    {"kana":"くすりをのみます","kanji":"薬を飲みます","meaning":"take medicine"},
    {"kana":"おふろにはいります","kanji":"お風呂に入ります","meaning":"take a bath"},
    {"kana":"たいせつ","kanji":"大切","meaning":"important"},
    {"kana":"だいじょうぶ","kanji":"大丈夫","meaning":"all right"},
    {"kana":"あぶない","kanji":"危ない","meaning":"dangerous"},
    {"kana":"もんだい","kanji":"問題","meaning":"problem"},
    {"kana":"こたえ","kanji":"答え","meaning":"answer"},
    {"kana":"きんえん","kanji":"禁煙","meaning":"no smoking"},
    {"kana":"ほけんしょう","kanji":"保険証","meaning":"insurance card"},
    {"kana":"かぜ","kanji":"風邪","meaning":"cold"},
    {"kana":"ねつ","kanji":"熱","meaning":"fever"},
    {"kana":"びょうき","kanji":"病気","meaning":"illness"},
    {"kana":"くすり","kanji":"薬","meaning":"medicine"},
    {"kana":"おふろ","kanji":"お風呂","meaning":"bath"},
    {"kana":"うわぎ","kanji":"上着","meaning":"jacket"},
    {"kana":"したぎ","kanji":"下着","meaning":"underwear"},
    {"kana":"いしゃ","kanji":"医者","meaning":"doctor"},
    {"kana":"すうじつ","kanji":"数日","meaning":"a few days"},
    {"kana":"〜にち","kanji":"〜日","meaning":"~ days"},
    {"kana":"〜までに","kanji":"〜までに","meaning":"before, by"},
    {"kana":"ですから","kanji":"ですから","meaning":"therefore"},
    {"kana":"どうしましたか","kanji":"どうしましたか","meaning":"what's the matter"},
    {"kana":"いたいです","kanji":"痛いです","meaning":"I have pain"},
    {"kana":"のど","kanji":"喉","meaning":"throat"},
    {"kana":"おだいじに","kanji":"お大事に","meaning":"take care of yourself"}
  ]
},

{
  "lesson": 18,
  "words": [
    {"kana":"できます","kanji":"出来ます","meaning":"can, be able to"},
    {"kana":"あらいます","kanji":"洗います","meaning":"wash"},
    {"kana":"ひきます","kanji":"弾きます","meaning":"play (musical instrument)"},
    {"kana":"うたいます","kanji":"歌います","meaning":"sing"},
    {"kana":"あつめます","kanji":"集めます","meaning":"collect"},
    {"kana":"すてます","kanji":"捨てます","meaning":"throw away"},
    {"kana":"かえます","kanji":"変えます","meaning":"change"},
    {"kana":"うんてんします","kanji":"運転します","meaning":"drive"},
    {"kana":"よやくします","kanji":"予約します","meaning":"reserve"},
    {"kana":"けんがくします","kanji":"見学します","meaning":"tour, observe"},
    {"kana":"ピアノ","kanji":"ピアノ","meaning":"piano"},
    {"kana":"メートル","kanji":"メートル","meaning":"meter"},
    {"kana":"こくさい","kanji":"国際","meaning":"international"},
    {"kana":"げんきん","kanji":"現金","meaning":"cash"},
    {"kana":"しゅみ","kanji":"趣味","meaning":"hobby"},
    {"kana":"にっき","kanji":"日記","meaning":"diary"},
    {"kana":"おいのり","kanji":"お祈り","meaning":"prayer"},
    {"kana":"かちょう","kanji":"課長","meaning":"section chief"},
    {"kana":"ぶちょう","kanji":"部長","meaning":"department head"},
    {"kana":"しゃちょう","kanji":"社長","meaning":"company president"},
    {"kana":"どうぶつ","kanji":"動物","meaning":"animal"},
    {"kana":"うま","kanji":"馬","meaning":"horse"},
    {"kana":"へえ","kanji":"へえ","meaning":"really"},
    {"kana":"それはおもしろいですね","kanji":"それは面白いですね","meaning":"that sounds interesting"},
    {"kana":"なかなか","kanji":"なかなか","meaning":"quite"},
    {"kana":"ほんとうですか","kanji":"本当ですか","meaning":"really"},
    {"kana":"ぜひ","kanji":"ぜひ","meaning":"by all means"}
  ]
},

{
  "lesson": 19,
  "words": [
    {"kana":"のぼります","kanji":"登ります","meaning":"climb"},
    {"kana":"とまります","kanji":"泊まります","meaning":"stay overnight"},
    {"kana":"そうじします","kanji":"掃除します","meaning":"clean"},
    {"kana":"せんたくします","kanji":"洗濯します","meaning":"wash clothes"},
    {"kana":"なります","kanji":"なります","meaning":"become"},
    {"kana":"かかります","kanji":"かかります","meaning":"take time / cost"},
    {"kana":"やすみます","kanji":"休みます","meaning":"take a rest"},
    {"kana":"いちど","kanji":"一度","meaning":"once"},
    {"kana":"いちども","kanji":"一度も","meaning":"not even once"},
    {"kana":"いつも","kanji":"いつも","meaning":"always"},
    {"kana":"ときどき","kanji":"時々","meaning":"sometimes"},
    {"kana":"それで","kanji":"それで","meaning":"therefore"},
    {"kana":"もちろん","kanji":"もちろん","meaning":"of course"},
    {"kana":"どうして","kanji":"どうして","meaning":"why"},
    {"kana":"ちょっと","kanji":"ちょっと","meaning":"a little"},
    {"kana":"きょうみ","kanji":"興味","meaning":"interest"},
    {"kana":"ぼく","kanji":"僕","meaning":"I (male informal)"},
    {"kana":"すばらしい","kanji":"素晴らしい","meaning":"wonderful"},
    {"kana":"みらい","kanji":"未来","meaning":"future"},
    {"kana":"まんが","kanji":"漫画","meaning":"manga"},
    {"kana":"アニメ","kanji":"アニメ","meaning":"anime"},
    {"kana":"ぶんか","kanji":"文化","meaning":"culture"},
    {"kana":"しぜん","kanji":"自然","meaning":"nature"},
    {"kana":"せかいじゅう","kanji":"世界中","meaning":"around the world"},
    {"kana":"じぶん","kanji":"自分","meaning":"oneself"},
    {"kana":"だれでも","kanji":"誰でも","meaning":"anyone"},
    {"kana":"どこでも","kanji":"どこでも","meaning":"anywhere"}
  ]
},

{
  "lesson": 20,
  "words": [
    {"kana":"いります","kanji":"要ります","meaning":"need"},
    {"kana":"しらべます","kanji":"調べます","meaning":"check, investigate"},
    {"kana":"しゅうりします","kanji":"修理します","meaning":"repair"},
    {"kana":"ぼく","kanji":"僕","meaning":"I (male informal)"},
    {"kana":"きみ","kanji":"君","meaning":"you (informal)"},
    {"kana":"〜くん","kanji":"〜君","meaning":"Mr. (for boys / young men)"},
    {"kana":"うん","kanji":"うん","meaning":"yes (casual)"},
    {"kana":"ううん","kanji":"ううん","meaning":"no (casual)"},
    {"kana":"ことば","kanji":"言葉","meaning":"word, language"},
    {"kana":"ぶっか","kanji":"物価","meaning":"prices"},
    {"kana":"きもの","kanji":"着物","meaning":"kimono"},
    {"kana":"ビザ","kanji":"ビザ","meaning":"visa"},
    {"kana":"はじめ","kanji":"初め","meaning":"beginning"},
    {"kana":"おわり","kanji":"終わり","meaning":"end"},
    {"kana":"こっち","kanji":"こっち","meaning":"this way (casual)"},
    {"kana":"そっち","kanji":"そっち","meaning":"that way (near you)"},
    {"kana":"あっち","kanji":"あっち","meaning":"that way (over there)"},
    {"kana":"どっち","kanji":"どっち","meaning":"which way"},
    {"kana":"みんなで","kanji":"皆で","meaning":"together"},
    {"kana":"〜けど","kanji":"〜けど","meaning":"but"},
    {"kana":"どうしても","kanji":"どうしても","meaning":"by all means"},
    {"kana":"もし","kanji":"もし","meaning":"if"},
    {"kana":"ほんとうに","kanji":"本当に","meaning":"really"},
    {"kana":"よかった","kanji":"よかった","meaning":"I'm glad"},
    {"kana":"じゃあ","kanji":"じゃあ","meaning":"well then"},
    {"kana":"またね","kanji":"またね","meaning":"see you"},
    {"kana":"げんきで","kanji":"元気で","meaning":"take care"},
    {"kana":"きっと","kanji":"きっと","meaning":"surely"}
  ]
},

{
  "lesson": 21,
  "words": [
    {"kana":"おもいます","kanji":"思います","meaning":"think"},
    {"kana":"いいます","kanji":"言います","meaning":"say"},
    {"kana":"かちます","kanji":"勝ちます","meaning":"win"},
    {"kana":"まけます","kanji":"負けます","meaning":"lose"},
    {"kana":"あります","kanji":"あります","meaning":"hold (event)"},
    {"kana":"やくにたちます","kanji":"役に立ちます","meaning":"be useful"},
    {"kana":"うごきます","kanji":"動きます","meaning":"move"},
    {"kana":"やめます","kanji":"辞めます","meaning":"quit"},
    {"kana":"きをつけます","kanji":"気を付けます","meaning":"be careful"},
    {"kana":"りゅうがくします","kanji":"留学します","meaning":"study abroad"},
    {"kana":"むだ","kanji":"無駄","meaning":"waste"},
    {"kana":"ふべん","kanji":"不便","meaning":"inconvenient"},
    {"kana":"すごい","kanji":"すごい","meaning":"great"},
    {"kana":"ほんとう","kanji":"本当","meaning":"truth"},
    {"kana":"うそ","kanji":"嘘","meaning":"lie"},
    {"kana":"じどうしゃ","kanji":"自動車","meaning":"car"},
    {"kana":"こうつう","kanji":"交通","meaning":"traffic"},
    {"kana":"ぶっか","kanji":"物価","meaning":"prices"},
    {"kana":"ニュース","kanji":"ニュース","meaning":"news"},
    {"kana":"アニメ","kanji":"アニメ","meaning":"anime"},
    {"kana":"マンガ","kanji":"漫画","meaning":"manga"},
    {"kana":"デザイン","kanji":"デザイン","meaning":"design"},
    {"kana":"ゆめ","kanji":"夢","meaning":"dream"},
    {"kana":"てんさい","kanji":"天才","meaning":"genius"},
    {"kana":"しあい","kanji":"試合","meaning":"match, game"},
    {"kana":"いけん","kanji":"意見","meaning":"opinion"},
    {"kana":"はなし","kanji":"話","meaning":"story"},
    {"kana":"ちきゅう","kanji":"地球","meaning":"earth"},
    {"kana":"つき","kanji":"月","meaning":"moon"},
    {"kana":"さいきん","kanji":"最近","meaning":"recently"},
    {"kana":"たぶん","kanji":"多分","meaning":"probably"},
    {"kana":"きっと","kanji":"きっと","meaning":"surely"},
    {"kana":"ほんとうに","kanji":"本当に","meaning":"really"},
    {"kana":"そんなに","kanji":"そんなに","meaning":"so much"},
    {"kana":"〜について","kanji":"〜について","meaning":"about"},
    {"kana":"もちろん","kanji":"もちろん","meaning":"of course"}
  ]
},

{
  "lesson": 22,
  "words": [
    {"kana":"きます","kanji":"着ます","meaning":"wear (shirt, jacket)"},
    {"kana":"はきます","kanji":"履きます","meaning":"wear (shoes, pants)"},
    {"kana":"かぶります","kanji":"被ります","meaning":"wear (hat)"},
    {"kana":"かけます","kanji":"掛けます","meaning":"wear (glasses)"},
    {"kana":"うまれます","kanji":"生まれます","meaning":"be born"},
    {"kana":"コート","kanji":"コート","meaning":"coat"},
    {"kana":"スーツ","kanji":"スーツ","meaning":"suit"},
    {"kana":"セーター","kanji":"セーター","meaning":"sweater"},
    {"kana":"ぼうし","kanji":"帽子","meaning":"hat"},
    {"kana":"めがね","kanji":"眼鏡","meaning":"glasses"},
    {"kana":"よく","kanji":"よく","meaning":"often"},
    {"kana":"ときどき","kanji":"時々","meaning":"sometimes"},
    {"kana":"そして","kanji":"そして","meaning":"and then"},
    {"kana":"それから","kanji":"それから","meaning":"after that"},
    {"kana":"どう","kanji":"どう","meaning":"how"},
    {"kana":"どんな","kanji":"どんな","meaning":"what kind of"},
    {"kana":"こちら","kanji":"こちら","meaning":"this way"},
    {"kana":"そちら","kanji":"そちら","meaning":"that way"},
    {"kana":"あちら","kanji":"あちら","meaning":"that way over there"},
    {"kana":"どちら","kanji":"どちら","meaning":"which way"},
    {"kana":"こちらは〜さんです","kanji":"こちらは〜さんです","meaning":"this is Mr./Ms.~"},
    {"kana":"よろしくおねがいします","kanji":"よろしくお願いします","meaning":"please treat me well"},
    {"kana":"しつれいします","kanji":"失礼します","meaning":"excuse me"}
  ]
},

{
  "lesson": 23,
  "words": [
    {"kana":"ききます","kanji":"聞きます","meaning":"ask"},
    {"kana":"まわします","kanji":"回します","meaning":"turn, rotate"},
    {"kana":"ひきます","kanji":"引きます","meaning":"pull"},
    {"kana":"かえます","kanji":"変えます","meaning":"change"},
    {"kana":"さわります","kanji":"触ります","meaning":"touch"},
    {"kana":"でます","kanji":"出ます","meaning":"come out"},
    {"kana":"うごきます","kanji":"動きます","meaning":"move"},
    {"kana":"あるきます","kanji":"歩きます","meaning":"walk"},
    {"kana":"わたります","kanji":"渡ります","meaning":"cross"},
    {"kana":"まがります","kanji":"曲がります","meaning":"turn"},
    {"kana":"でんき","kanji":"電気","meaning":"electricity"},
    {"kana":"ガス","kanji":"ガス","meaning":"gas"},
    {"kana":"みち","kanji":"道","meaning":"road"},
    {"kana":"こうさてん","kanji":"交差点","meaning":"intersection"},
    {"kana":"しんごう","kanji":"信号","meaning":"traffic light"},
    {"kana":"かど","kanji":"角","meaning":"corner"},
    {"kana":"はし","kanji":"橋","meaning":"bridge"},
    {"kana":"ちゅうしゃじょう","kanji":"駐車場","meaning":"parking lot"},
    {"kana":"たてもの","kanji":"建物","meaning":"building"},
    {"kana":"くうこう","kanji":"空港","meaning":"airport"},
    {"kana":"ちず","kanji":"地図","meaning":"map"},
    {"kana":"ゆうびんきょく","kanji":"郵便局","meaning":"post office"},
    {"kana":"ぎんこう","kanji":"銀行","meaning":"bank"},
    {"kana":"としょかん","kanji":"図書館","meaning":"library"},
    {"kana":"こうえん","kanji":"公園","meaning":"park"},
    {"kana":"まっすぐ","kanji":"真っ直ぐ","meaning":"straight"},
    {"kana":"ゆっくり","kanji":"ゆっくり","meaning":"slowly"},
    {"kana":"すぐ","kanji":"すぐ","meaning":"immediately"},
    {"kana":"ここ","kanji":"ここ","meaning":"here"},
    {"kana":"そこ","kanji":"そこ","meaning":"there"},
    {"kana":"あそこ","kanji":"あそこ","meaning":"over there"},
    {"kana":"どこ","kanji":"どこ","meaning":"where"},
    {"kana":"こちら","kanji":"こちら","meaning":"this way"},
    {"kana":"そちら","kanji":"そちら","meaning":"that way"},
    {"kana":"あちら","kanji":"あちら","meaning":"that way over there"},
    {"kana":"どちら","kanji":"どちら","meaning":"which way"},
    {"kana":"すみません","kanji":"すみません","meaning":"excuse me"},
    {"kana":"どうやっていきますか","kanji":"どうやって行きますか","meaning":"how do you go"},
    {"kana":"おしえてください","kanji":"教えてください","meaning":"please tell me"}
  ]
},

{
  "lesson": 24,
  "words": [
    {"kana":"くれます","kanji":"くれます","meaning":"give (to me)"},
    {"kana":"つれていきます","kanji":"連れて行きます","meaning":"take someone"},
    {"kana":"つれてきます","kanji":"連れて来ます","meaning":"bring someone"},
    {"kana":"おくります","kanji":"送ります","meaning":"see someone off"},
    {"kana":"しょうかいします","kanji":"紹介します","meaning":"introduce"},
    {"kana":"あんないします","kanji":"案内します","meaning":"show around"},
    {"kana":"せつめいします","kanji":"説明します","meaning":"explain"},
    {"kana":"おじいさん","kanji":"お爺さん","meaning":"grandfather"},
    {"kana":"おばあさん","kanji":"お婆さん","meaning":"grandmother"},
    {"kana":"じゅんび","kanji":"準備","meaning":"preparation"},
    {"kana":"いみ","kanji":"意味","meaning":"meaning"},
    {"kana":"おかし","kanji":"お菓子","meaning":"sweets"},
    {"kana":"ぜんぶ","kanji":"全部","meaning":"all"},
    {"kana":"じぶんで","kanji":"自分で","meaning":"by oneself"},
    {"kana":"ほかに","kanji":"他に","meaning":"besides"},
    {"kana":"ワゴン","kanji":"ワゴン","meaning":"wagon"},
    {"kana":"おべんとう","kanji":"お弁当","meaning":"boxed lunch"},
    {"kana":"おちゃ","kanji":"お茶","meaning":"tea"},
    {"kana":"かんこう","kanji":"観光","meaning":"sightseeing"},
    {"kana":"ガイド","kanji":"ガイド","meaning":"guide"},
    {"kana":"せつめい","kanji":"説明","meaning":"explanation"},
    {"kana":"はなし","kanji":"話","meaning":"story"},
    {"kana":"ちょっと","kanji":"ちょっと","meaning":"a little"},
    {"kana":"いま","kanji":"今","meaning":"now"},
    {"kana":"あとで","kanji":"後で","meaning":"later"},
    {"kana":"もうすぐ","kanji":"もうすぐ","meaning":"soon"},
    {"kana":"よかったですね","kanji":"よかったですね","meaning":"that's good"},
    {"kana":"たのしかった","kanji":"楽しかった","meaning":"was fun"},
    {"kana":"ありがとう","kanji":"ありがとう","meaning":"thank you"}
  ]
},

{
  "lesson": 25,
  "words": [
    {"kana":"かんがえます","kanji":"考えます","meaning":"think, consider"},
    {"kana":"つきます","kanji":"着きます","meaning":"arrive"},
    {"kana":"とります","kanji":"取ります","meaning":"take (time, vacation)"},
    {"kana":"たります","kanji":"足ります","meaning":"be enough"},
    {"kana":"いなか","kanji":"田舎","meaning":"countryside"},
    {"kana":"とちゅう","kanji":"途中","meaning":"on the way"},
    {"kana":"やまみち","kanji":"山道","meaning":"mountain road"},
    {"kana":"みずうみ","kanji":"湖","meaning":"lake"},
    {"kana":"いけ","kanji":"池","meaning":"pond"},
    {"kana":"みなと","kanji":"港","meaning":"harbor"},
    {"kana":"ゆうびんきょく","kanji":"郵便局","meaning":"post office"},
    {"kana":"デパート","kanji":"デパート","meaning":"department store"},
    {"kana":"レストラン","kanji":"レストラン","meaning":"restaurant"},
    {"kana":"ホテル","kanji":"ホテル","meaning":"hotel"},
    {"kana":"おてら","kanji":"お寺","meaning":"temple"},
    {"kana":"じんじゃ","kanji":"神社","meaning":"shrine"},
    {"kana":"しぜん","kanji":"自然","meaning":"nature"},
    {"kana":"けしき","kanji":"景色","meaning":"scenery"},
    {"kana":"はしります","kanji":"走ります","meaning":"run"},
    {"kana":"あそびます","kanji":"遊びます","meaning":"play"},
    {"kana":"りょこうします","kanji":"旅行します","meaning":"travel"},
    {"kana":"とても","kanji":"とても","meaning":"very"},
    {"kana":"あまり","kanji":"あまり","meaning":"not so"},
    {"kana":"ほんとうに","kanji":"本当に","meaning":"really"},
    {"kana":"きっと","kanji":"きっと","meaning":"surely"},
    {"kana":"もちろん","kanji":"もちろん","meaning":"of course"},
    {"kana":"よかった","kanji":"よかった","meaning":"I'm glad"},
    {"kana":"たのしい","kanji":"楽しい","meaning":"fun"},
    {"kana":"うれしい","kanji":"嬉しい","meaning":"happy"},
    {"kana":"ざんねん","kanji":"残念","meaning":"unfortunate"}
  ]
}
]
